plover_tapey_tape.py
plover_tapey_tape-0.0.6.dist-info/LICENSE
plover_tapey_tape-0.0.6.dist-info/METADATA
plover_tapey_tape-0.0.6.dist-info/WHEEL
plover_tapey_tape-0.0.6.dist-info/entry_points.txt
plover_tapey_tape-0.0.6.dist-info/top_level.txt
plover_tapey_tape-0.0.6.dist-info/zip-safe
plover_tapey_tape-0.0.6.dist-info/RECORD
