Metadata-Version: 2.1
Name: plover-tapey-tape
Version: 0.0.6
Summary: Paper tape with extra information
Home-page: https://github.com/rabbitgrowth/plover-tapey-tape
Author: rabbitgrowth
Author-email: ytknick@gmail.com
License: GNU General Public License v3 (GPLv3)
Keywords: plover plover_plugin
Platform: UNKNOWN
License-File: LICENSE
Requires-Dist: plover (>=4.0.0.dev10)
